awesomplete/__init__.py
awesomplete/widgets.py
awesomplete/static/awesomplete/css/widget.css
awesomplete/static/awesomplete/css/vendor/awesomplete.css
awesomplete/static/awesomplete/js/widget.js
awesomplete/static/awesomplete/js/vendor/awesomplete.js
awesomplete/static/awesomplete/js/vendor/awesomplete.min.js
awesomplete/static/awesomplete/js/vendor/awesomplete.min.js.map
awesomplete/templates/awesomplete/widget_wrapper.html
django_awesomplete-0.6.0.dist-info/LICENSE
django_awesomplete-0.6.0.dist-info/METADATA
django_awesomplete-0.6.0.dist-info/WHEEL
django_awesomplete-0.6.0.dist-info/top_level.txt
django_awesomplete-0.6.0.dist-info/RECORD
